[
  {
    "id": "gipu-tolosa",
    "name": "Tolosaldea",
    "community": "País Vasco",
    "province": "Gipuzkoa",
    "zone": "Interior Norte",
    "idealistaSlug": "tolosaldea",
    "description": "Tolosa, capital histórica y alubias famosas. Interior verde bien comunicado a precio inferior a la costa.",
    "vibe": "Histórico, txoko, tranquilo.",
    "priceM2": 3200,
    "yoyPrice": 10,
    "tempAvg": 12.5,
    "sunHours": 1850,
    "rainfall": 1500,
    "popTrend": 0,
    "density": 150,
    "fiber": 96,
    "hospitalKm": 15,
    "airportKm": 35,
    "protected": null,
    "beauty": 7,
    "beachKm": 0
  },
  {
    "id": "gipu-goierri",
    "name": "Goierri",
    "community": "País Vasco",
    "province": "Gipuzkoa",
    "zone": "Interior Alto",
    "idealistaSlug": "goierri",
    "description": "Caseríos y montaña. Cuna del Idiazábal y los valores rurales vascos más arraigados. El más asequible.",
    "vibe": "Caserío, queso, aislado.",
    "priceM2": 2800,
    "yoyPrice": 10,
    "tempAvg": 11,
    "sunHours": 1900,
    "rainfall": 1500,
    "popTrend": 0,
    "density": 75,
    "fiber": 92,
    "hospitalKm": 20,
    "airportKm": 50,
    "protected": null,
    "beauty": 8,
    "beachKm": 0
  },
  {
    "id": "gipu-bajo-deba",
    "name": "Bajo Deba",
    "community": "País Vasco",
    "province": "Gipuzkoa",
    "zone": "Costa Oeste",
    "idealistaSlug": "bajo-deba",
    "description": "Deba y Mutriku en acantilados sobre el Cantábrico. Pueblos de pescadores con precios algo inferiores.",
    "vibe": "Marinero, acantilado, auténtico.",
    "priceM2": 3000,
    "yoyPrice": 11,
    "tempAvg": 13.5,
    "sunHours": 1750,
    "rainfall": 1400,
    "popTrend": -1,
    "density": 250,
    "fiber": 95,
    "hospitalKm": 15,
    "airportKm": 50,
    "protected": null,
    "beauty": 9,
    "beachKm": 10
  },
  {
    "id": "gipu-alto-deba",
    "name": "Alto Deba",
    "community": "País Vasco",
    "province": "Gipuzkoa",
    "zone": "Interior Industrial",
    "idealistaSlug": "alto-deba",
    "description": "Mondragón y Bergara, la cooperativa obrera más grande del mundo. Stock industrial a precios bajos.",
    "vibe": "Cooperativista, industrial, sobrio.",
    "priceM2": 2500,
    "yoyPrice": 10,
    "tempAvg": 12,
    "sunHours": 1900,
    "rainfall": 1400,
    "popTrend": -1,
    "density": 200,
    "fiber": 97,
    "hospitalKm": 10,
    "airportKm": 45,
    "protected": null,
    "beauty": 7,
    "beachKm": null
  },
  {
    "id": "bizk-lea",
    "name": "Lea-Artibai",
    "community": "País Vasco",
    "province": "Bizkaia",
    "zone": "Costa Este",
    "idealistaSlug": "lea-artibai",
    "description": "Lekeitio y Ondarroa: playas entre acantilados y villas pesqueras vascas con sabor auténtico.",
    "vibe": "Marinero, festivo, identitario.",
    "priceM2": 2800,
    "yoyPrice": 11,
    "tempAvg": 13.5,
    "sunHours": 1750,
    "rainfall": 1350,
    "popTrend": -2,
    "density": 120,
    "fiber": 92,
    "hospitalKm": 20,
    "airportKm": 45,
    "protected": null,
    "beauty": 9,
    "beachKm": 20
  },
  {
    "id": "bizk-durango",
    "name": "Duranguesado",
    "community": "País Vasco",
    "province": "Bizkaia",
    "zone": "Valle Interior",
    "idealistaSlug": "duranguesado",
    "description": "Durango y el valle industrial más verde del País Vasco. Conexión directa a Bilbao en 20 min.",
    "vibe": "Industrial vasco, verde, eficiente.",
    "priceM2": 2600,
    "yoyPrice": 10,
    "tempAvg": 12,
    "sunHours": 1800,
    "rainfall": 1400,
    "popTrend": 1,
    "density": 250,
    "fiber": 97,
    "hospitalKm": 10,
    "airportKm": 30,
    "protected": null,
    "beauty": 7,
    "beachKm": null
  },
  {
    "id": "bizk-busturi",
    "name": "Busturialdea",
    "community": "País Vasco",
    "province": "Bizkaia",
    "zone": "Reserva Biosfera",
    "idealistaSlug": "busturialdea",
    "description": "Urdaibai, Bermeo y Mundaka. Reserva de Biosfera con la ola de izquierda más famosa de Europa.",
    "vibe": "Protegido, surfero, estuario.",
    "priceM2": 3400,
    "yoyPrice": 11,
    "tempAvg": 13.5,
    "sunHours": 1750,
    "rainfall": 1300,
    "popTrend": 1,
    "density": 145,
    "fiber": 94,
    "hospitalKm": 15,
    "airportKm": 35,
    "protected": "RB",
    "beauty": 10,
    "beachKm": 20
  },
  {
    "id": "bizk-uribe",
    "name": "Uribe-Butrón",
    "community": "País Vasco",
    "province": "Bizkaia",
    "zone": "Costa Norte",
    "idealistaSlug": "uribe-butroe",
    "description": "Getxo, Plentzia y Las Arenas: la costa residencial del gran Bilbao. Tren directo al centro en 20 min.",
    "vibe": "Residencial, costero, exclusivo.",
    "priceM2": 4000,
    "yoyPrice": 11,
    "tempAvg": 14,
    "sunHours": 1750,
    "rainfall": 1200,
    "popTrend": 2,
    "density": 600,
    "fiber": 99,
    "hospitalKm": 8,
    "airportKm": 15,
    "protected": null,
    "beauty": 8,
    "beachKm": 10
  },
  {
    "id": "bizk-bilbao",
    "name": "Gran Bilbao",
    "community": "País Vasco",
    "province": "Bizkaia",
    "zone": "Área Metropolitana",
    "idealistaSlug": "gran-bilbao",
    "description": "Guggenheim, gastronomía y ría reconvertida. La reinvención urbana más exitosa de España.",
    "vibe": "Cosmopolita, reinventado, vasco.",
    "priceM2": 3500,
    "yoyPrice": 11,
    "tempAvg": 13.5,
    "sunHours": 1700,
    "rainfall": 1200,
    "popTrend": 2,
    "density": 1200,
    "fiber": 99,
    "hospitalKm": 3,
    "airportKm": 12,
    "protected": null,
    "beauty": 7,
    "beachKm": 0
  },
  {
    "id": "bizk-arratia",
    "name": "Arratia-Nervión",
    "community": "País Vasco",
    "province": "Bizkaia",
    "zone": "Interior Oeste",
    "idealistaSlug": "arratia-nervion",
    "description": "Valle alto del Nervión entre caseríos y robledales. El Bizkaia más rural y asequible.",
    "vibe": "Caserío, verde, apartado.",
    "priceM2": 2200,
    "yoyPrice": 10,
    "tempAvg": 12,
    "sunHours": 1800,
    "rainfall": 1500,
    "popTrend": -5,
    "density": 60,
    "fiber": 88,
    "hospitalKm": 20,
    "airportKm": 35,
    "protected": null,
    "beauty": 8,
    "beachKm": null
  }
]